<Container>
    <Position>(0, 0)</Position>
    <Size>(1280, 720)</Size>
    <Children>
        <Label>
            <Position>(0, 676)</Position>
            <Size>(1280, 40)</Size>
            <Text>"The Wizard of the North"</Text>
            <FontSize>40</FontSize>
            <Color>000000FF</Color>
            <BorderColor>FF0000FF</BorderColor>
            <BackColor>0000FFFF</BackColor>
            <HAlignment>CENTER</HAlignment>
            <UseFontSize>false</UseFontSize>
        </Label>
        <ImageLabel>
            <Position>(30, 30)</Position>
            <Size>(224, 98)</Size>
            <TextureFile>"ui/PlayBTN.png"</TextureFile>
            <BackColor>FF0000FF</BackColor>
            <ImageAlignment>STRETCHED</ImageAlignment>
        </ImageLabel>
    </Children>
</Container>
